{"expireTime":9007200855236364000,"key":"gatsby-plugin-mdx-entire-payload-d4718a5eb805901cf34f0208fa92c99a-","val":{"mdast":{"type":"root","children":[{"type":"import","value":"import DefaultLayout from \"/Users/uma.krishnan/projects/uma/entable-components/node_modules/gatsby-theme-docz/src/base/Layout.js\"","position":{"start":{"line":3,"column":1,"offset":2},"end":{"line":3,"column":130,"offset":131},"indent":[]}},{"type":"export","default":true,"value":"export default DefaultLayout","position":{"start":{"line":5,"column":1,"offset":133},"end":{"line":5,"column":29,"offset":161},"indent":[]}},{"type":"code","lang":"jsx","meta":null,"value":"  <AspectRatio ratio=\"300/165\" style={{ maxWidth: '300px', margin: 'auto' }}>\n    <img\n      src=\"https://upload.wikimedia.org/wikipedia/en/7/7d/Minions_characters.png\"\n      alt=\"demo\"\n    />\n  </AspectRatio>\n\n\nexport const _frontmatter = {}","position":{"start":{"line":7,"column":1,"offset":163},"end":{"line":16,"column":31,"offset":412},"indent":[1,1,1,1,1,1,1,1,1]}}],"position":{"start":{"line":1,"column":1,"offset":0},"end":{"line":16,"column":31,"offset":412}}},"scopeImports":[],"scopeIdentifiers":[],"rawMDXOutput":"/* @jsx mdx */\nimport { mdx } from '@mdx-js/react';\n/* @jsx mdx */\nimport DefaultLayout from \"/Users/uma.krishnan/projects/uma/entable-components/node_modules/gatsby-theme-docz/src/base/Layout.js\"\n\n\nconst layoutProps = {\n  \n};\nconst MDXLayout = DefaultLayout\nexport default function MDXContent({\n  components,\n  ...props\n}) {\n  return <MDXLayout {...layoutProps} {...props} components={components} mdxType=\"MDXLayout\">\n\n\n    <pre><code parentName=\"pre\" {...{\n        \"className\": \"language-jsx\"\n      }}>{`  <AspectRatio ratio=\"300/165\" style={{ maxWidth: '300px', margin: 'auto' }}>\n    <img\n      src=\"https://upload.wikimedia.org/wikipedia/en/7/7d/Minions_characters.png\"\n      alt=\"demo\"\n    />\n  </AspectRatio>\n\n\nexport const _frontmatter = {}\n`}</code></pre>\n    </MDXLayout>;\n}\n\n;\nMDXContent.isMDXComponent = true;"}}